biosimulations_bigg/__init__.py
biosimulations_bigg/__main__.py
biosimulations_bigg/_version.py
biosimulations_bigg/config.py
biosimulations_bigg/core.py
biosimulations_bigg/final/curators.yml
biosimulations_bigg/final/extra-visualizations.yml
biosimulations_bigg/final/issues.yml
biosimulations_bigg/final/status.yml
biosimulations_bigg/final/thumbnails.yml
biosimulations_bigg/source/LICENSE
biosimulations_bigg-0.0.5.dist-info/LICENSE
biosimulations_bigg-0.0.5.dist-info/METADATA
biosimulations_bigg-0.0.5.dist-info/WHEEL
biosimulations_bigg-0.0.5.dist-info/entry_points.txt
biosimulations_bigg-0.0.5.dist-info/top_level.txt
biosimulations_bigg-0.0.5.dist-info/RECORD
